innate/__init__.py
innate/approximation.py
innate/changelog.txt
innate/config.toml
innate/io.py
innate/main.py
innate/plotting.py
innate/read_files.py
innate/string_to_function.py
innate/tools.py
innate/interpolation/__init__.py
innate/interpolation/methods.py
innate/interpolation/pytensor.py
innate/regression/__init__.py
innate/regression/methods.py
innate/torch/siren.py
innate/torch/siren_train_image.py
innate/torch/siren_train_ngrid.py
innate/torch/torch_tools.py
innate_stable-0.2.1.dist-info/licenses/LICENSE.rst
innate_stable-0.2.1.dist-info/METADATA
innate_stable-0.2.1.dist-info/WHEEL
innate_stable-0.2.1.dist-info/top_level.txt
innate_stable-0.2.1.dist-info/RECORD
