Metadata-Version: 2.4
Name: innate-stable
Version: 0.2.1
Summary: Interpolator and Neural Network Architecture for TEnsors
Author-email: Vital Fernández <vgf@umich.edu>
License-Expression: GPL-3.0-or-later
Classifier: Programming Language :: Python :: 3
Classifier: Programming Language :: Python :: 3.11
Requires-Python: >=3.10
License-File: LICENSE.rst
Requires-Dist: numpy~=2.2
Requires-Dist: h5py~=3.11
Requires-Dist: bokeh~=3.6
Requires-Dist: h5netcdf~=1.3
Requires-Dist: tomli>=2.0.0; python_version < "3.11"
Dynamic: license-file
